[{"score":"Pale Chartreuse Tabby-Pouncing","count":65},{"score":"Sky Blue Tortie-Stalking","count":65},{"score":"Chartreuse Tabby-Stalking","count":60},{"score":"Pale Fuchsia Tortie-Pouncing","count":79},{"score":"Pale Blue Tortie-Stalking","count":85},{"score":"Pale Yellow Tortie-Sleeping","count":69},{"score":"Pale Magenta Spotted-Standing","count":64},{"score":"Pale Chartreuse Tortie-Standing","count":54},{"score":"Pale Orange Tabby-Sleeping","count":49},{"score":"Orange Tortie-Sleeping","count":69},{"score":"Blue Tabby-Stalking","count":50},{"score":"Chartreuse Pure-Standing","count":71},{"score":"Pale Red Pure-Standing","count":54},{"score":"Pale Chartreuse Pure-Pouncing","count":69},{"score":"Pale Teal Spotted-Pouncing","count":69},{"score":"Orange Tortie-Standing","count":75},{"score":"Red Tabby-Standing","count":74},{"score":"Teal Pure-Sleeping","count":49},{"score":"Orange Spotted-Standing","count":64},{"score":"Fuchsia Pure-Stalking","count":72},{"score":"Pale Fuchsia Tabby-Pouncing","count":77},{"score":"Pale Red Pure-Sleeping","count":64},{"score":"Pale Orange Pure-Stalking","count":69},{"score":"Red Pure-Pouncing","count":85},{"score":"Green Tortie-Sleeping","count":70},{"score":"Sky Blue Spotted-Sleeping","count":67},{"score":"Pale Purple Pure-Stalking","count":90},{"score":"Pale Fuchsia Pure-Standing","count":61},{"score":"Teal Spotted-Sleeping","count":38},{"score":"Red Tortie-Standing","count":83},{"score":"Pale Cyan Tortie-Stalking","count":76},{"score":"Pale Chartreuse Pure-Stalking","count":67},{"score":"Pale Chartreuse Pure-Standing","count":63},{"score":"Sky Blue Tabby-Standing","count":58},{"score":"Magenta Spotted-Sleeping","count":57},{"score":"Cyan Tortie-Sleeping","count":63},{"score":"Pale Fuchsia Tabby-Stalking","count":54},{"score":"Pale Yellow Tortie-Stalking","count":68},{"score":"Sky Blue Tortie-Sleeping","count":78},{"score":"Pale Cyan Tabby-Sleeping","count":51},{"score":"Cyan Tabby-Standing","count":67},{"score":"Cyan Tabby-Stalking","count":70},{"score":"Pale Yellow Pure-Stalking","count":72},{"score":"Fuchsia Pure-Standing","count":68},{"score":"Chartreuse Tabby-Standing","count":52},{"score":"Pale Blue Pure-Stalking","count":79},{"score":"Blue Pure-Pouncing","count":63},{"score":"Pale Chartreuse Spotted-Stalking","count":53},{"score":"Yellow Tortie-Stalking","count":79},{"score":"Yellow Spotted-Stalking","count":58},{"score":"Pale Sky Blue Tabby-Pouncing","count":76},{"score":"Pale Sky Blue Tortie-Sleeping","count":58},{"score":"Pale Red Tortie-Sleeping","count":62},{"score":"Pale Sky Blue Spotted-Pouncing","count":79},{"score":"Pale Purple Pure-Standing","count":74},{"score":"Purple Tabby-Sleeping","count":63},{"score":"Fuchsia Pure-Pouncing","count":84},{"score":"Purple Tabby-Standing","count":60},{"score":"Orange Pure-Stalking","count":76},{"score":"Pale Cyan Tortie-Standing","count":85},{"score":"Pale Blue Tortie-Standing","count":66},{"score":"Pale Purple Spotted-Stalking","count":61},{"score":"Pale Chartreuse Spotted-Standing","count":53},{"score":"Pale Magenta Pure-Sleeping","count":55},{"score":"Pale Yellow Spotted-Sleeping","count":44},{"score":"Pale Green Tabby-Sleeping","count":70},{"score":"Pale Teal Tortie-Pouncing","count":68},{"score":"Pale Purple Spotted-Sleeping","count":81},{"score":"Pale Blue Tabby-Pouncing","count":70},{"score":"Chartreuse Tortie-Stalking","count":58},{"score":"Sky Blue Tabby-Stalking","count":59},{"score":"Pale Sky Blue Pure-Sleeping","count":76},{"score":"Green Spotted-Stalking","count":65},{"score":"Sky Blue Spotted-Pouncing","count":75},{"score":"Orange Tabby-Stalking","count":78},{"score":"Teal Tabby-Sleeping","count":57},{"score":"Black Pure-Standing","count":6},{"score":"Pale White Pure-Sleeping","count":6},{"score":"Black Pure-Pouncing","count":6},{"score":"Pale White Pure-Stalking","count":6},{"score":"Black Tabby-Standing","count":6},{"score":"Pale White Tabby-Sleeping","count":6},{"score":"Black Tabby-Pouncing","count":6},{"score":"Pale White Tabby-Stalking","count":6},{"score":"Black Spotted-Standing","count":6},{"score":"Pale White Spotted-Sleeping","count":6},{"score":"Black Spotted-Pouncing","count":6},{"score":"Pale White Spotted-Stalking","count":6},{"score":"Black Tortie-Standing","count":6},{"score":"Pale White Tortie-Sleeping","count":6},{"score":"Black Tortie-Pouncing","count":6},{"score":"Pale White Tortie-Stalking","count":6},{"score":"Pale Fuchsia Tabby-Sleeping","count":63},{"score":"Sky Blue Pure-Standing","count":60},{"score":"Orange Pure-Pouncing","count":89},{"score":"Pale Green Spotted-Standing","count":46},{"score":"Red Tabby-Pouncing","count":67},{"score":"Pale Yellow Tabby-Standing","count":52},{"score":"Pale Cyan Pure-Pouncing","count":54},{"score":"Cyan Tabby-Pouncing","count":70},{"score":"Purple Spotted-Standing","count":61},{"score":"Pale Teal Tabby-Pouncing","count":60},{"score":"Green Tortie-Stalking","count":72},{"score":"Magenta Tabby-Standing","count":66},{"score":"Pale Green Pure-Standing","count":52},{"score":"Cyan Tortie-Pouncing","count":86},{"score":"Cyan Pure-Stalking","count":103},{"score":"Pale Green Pure-Pouncing","count":72},{"score":"Teal Tabby-Standing","count":72},{"score":"Cyan Tabby-Sleeping","count":69},{"score":"Pale Purple Pure-Sleeping","count":61},{"score":"Magenta Spotted-Standing","count":61},{"score":"Pale Orange Tortie-Pouncing","count":88},{"score":"Pale Chartreuse Tortie-Stalking","count":66},{"score":"Pale Teal Tabby-Standing","count":40},{"score":"Teal Tabby-Pouncing","count":53},{"score":"Pale Sky Blue Pure-Pouncing","count":65},{"score":"Pale Green Tabby-Pouncing","count":64},{"score":"Magenta Tabby-Sleeping","count":54},{"score":"Purple Pure-Stalking","count":75},{"score":"Red Pure-Standing","count":70},{"score":"Teal Tabby-Stalking","count":70},{"score":"Pale Green Spotted-Stalking","count":59},{"score":"Chartreuse Spotted-Sleeping","count":58},{"score":"Pale Red Spotted-Standing","count":80},{"score":"Yellow Tortie-Pouncing","count":76},{"score":"Pale Magenta Pure-Standing","count":53},{"score":"Pale Magenta Spotted-Stalking","count":72},{"score":"Pale Teal Tortie-Stalking","count":68},{"score":"Yellow Tabby-Sleeping","count":56},{"score":"Purple Pure-Sleeping","count":74},{"score":"Green Spotted-Sleeping","count":51},{"score":"Blue Spotted-Sleeping","count":65},{"score":"Pale Cyan Spotted-Stalking","count":63},{"score":"Pale Chartreuse Tabby-Stalking","count":48},{"score":"Fuchsia Tortie-Stalking","count":88},{"score":"Pale Purple Tabby-Pouncing","count":53},{"score":"Pale Blue Tabby-Stalking","count":65},{"score":"Pale Orange Spotted-Sleeping","count":54},{"score":"Yellow Pure-Stalking","count":78},{"score":"Pale Orange Spotted-Standing","count":64},{"score":"Pale Red Tabby-Standing","count":55},{"score":"Fuchsia Spotted-Standing","count":55},{"score":"Pale Magenta Spotted-Pouncing","count":66},{"score":"Pale Yellow Tortie-Standing","count":79},{"score":"Pale Purple Tortie-Standing","count":63},{"score":"Pale Chartreuse Tortie-Pouncing","count":56},{"score":"Purple Spotted-Pouncing","count":81},{"score":"Cyan Spotted-Stalking","count":66},{"score":"Pale Red Spotted-Sleeping","count":59},{"score":"Pale Cyan Tortie-Sleeping","count":70},{"score":"Red Tabby-Sleeping","count":74},{"score":"Magenta Tortie-Standing","count":57},{"score":"Green Tortie-Pouncing","count":62},{"score":"Cyan Pure-Standing","count":63},{"score":"Pale Yellow Spotted-Stalking","count":51},{"score":"Pale Red Pure-Pouncing","count":61},{"score":"Pale Sky Blue Pure-Standing","count":95},{"score":"Pale Blue Spotted-Stalking","count":59},{"score":"Pale Purple Tortie-Pouncing","count":74},{"score":"Purple Pure-Pouncing","count":80},{"score":"Pale Green Spotted-Pouncing","count":74},{"score":"Pale Orange Spotted-Stalking","count":58},{"score":"Pale Yellow Pure-Pouncing","count":88},{"score":"Sky Blue Pure-Stalking","count":77},{"score":"Pale Fuchsia Pure-Pouncing","count":64},{"score":"Pale Red Tortie-Standing","count":69},{"score":"Yellow Tortie-Standing","count":66},{"score":"Pale Green Pure-Stalking","count":48},{"score":"Fuchsia Tortie-Sleeping","count":59},{"score":"Pale Green Tortie-Pouncing","count":59},{"score":"Purple Tortie-Sleeping","count":66},{"score":"Pale Fuchsia Spotted-Pouncing","count":81},{"score":"Pale Chartreuse Tortie-Sleeping","count":61},{"score":"Pale Blue Tabby-Sleeping","count":84},{"score":"Pale Sky Blue Tortie-Standing","count":84},{"score":"Purple Tortie-Standing","count":65},{"score":"Cyan Tortie-Standing","count":65},{"score":"Pale Fuchsia Tabby-Standing","count":55},{"score":"Chartreuse Pure-Pouncing","count":61},{"score":"Cyan Spotted-Sleeping","count":59},{"score":"Pale Fuchsia Spotted-Sleeping","count":63},{"score":"Teal Spotted-Standing","count":65},{"score":"Magenta Tortie-Sleeping","count":69},{"score":"Pale Fuchsia Pure-Sleeping","count":72},{"score":"Pale Cyan Pure-Stalking","count":69},{"score":"Pale Purple Tortie-Stalking","count":58},{"score":"Teal Pure-Standing","count":57},{"score":"Red Spotted-Stalking","count":76},{"score":"Pale Purple Pure-Pouncing","count":77},{"score":"Pale Yellow Tortie-Pouncing","count":72},{"score":"Sky Blue Spotted-Standing","count":65},{"score":"Red Spotted-Pouncing","count":64},{"score":"Teal Spotted-Stalking","count":64},{"score":"Sky Blue Pure-Pouncing","count":58},{"score":"Pale Green Tortie-Standing","count":52},{"score":"Teal Pure-Pouncing","count":62},{"score":"Fuchsia Tortie-Standing","count":72},{"score":"Pale Purple Tabby-Standing","count":71},{"score":"Pale Red Spotted-Stalking","count":59},{"score":"Magenta Pure-Sleeping","count":66},{"score":"Pale Yellow Spotted-Standing","count":76},{"score":"Pale Fuchsia Spotted-Standing","count":60},{"score":"Red Tortie-Sleeping","count":51},{"score":"Cyan Spotted-Standing","count":57},{"score":"Blue Spotted-Pouncing","count":64},{"score":"Pale Magenta Pure-Stalking","count":67},{"score":"Pale Cyan Spotted-Standing","count":58},{"score":"Red Pure-Stalking","count":86},{"score":"Chartreuse Pure-Sleeping","count":61},{"score":"Cyan Pure-Pouncing","count":75},{"score":"Fuchsia Spotted-Sleeping","count":61},{"score":"Orange Pure-Standing","count":60},{"score":"Fuchsia Spotted-Pouncing","count":56},{"score":"Pale Magenta Tortie-Standing","count":67},{"score":"Pale Chartreuse Spotted-Sleeping","count":49},{"score":"Fuchsia Tortie-Pouncing","count":63},{"score":"Pale Blue Spotted-Sleeping","count":75},{"score":"Green Pure-Stalking","count":56},{"score":"Yellow Tabby-Standing","count":67},{"score":"Red Tabby-Stalking","count":82},{"score":"Pale Sky Blue Tabby-Standing","count":71},{"score":"Cyan Spotted-Pouncing","count":83},{"score":"Pale Magenta Spotted-Sleeping","count":56},{"score":"Pale Cyan Tabby-Stalking","count":88},{"score":"Pale Orange Pure-Pouncing","count":74},{"score":"Teal Spotted-Pouncing","count":63},{"score":"Pale Yellow Pure-Standing","count":63},{"score":"Orange Spotted-Stalking","count":86},{"score":"Pale Sky Blue Spotted-Standing","count":62},{"score":"Pale Green Tortie-Sleeping","count":53},{"score":"Teal Tortie-Sleeping","count":62},{"score":"Pale Purple Tabby-Sleeping","count":55},{"score":"Cyan Tortie-Stalking","count":79},{"score":"Pale Teal Tabby-Stalking","count":72},{"score":"Chartreuse Pure-Stalking","count":65},{"score":"Pale Magenta Tortie-Pouncing","count":65},{"score":"Pale Yellow Tabby-Stalking","count":55},{"score":"Chartreuse Tabby-Pouncing","count":70},{"score":"Pale Red Tabby-Sleeping","count":69},{"score":"Pale Magenta Tabby-Standing","count":56},{"score":"Green Tabby-Standing","count":61},{"score":"Pale Orange Tortie-Sleeping","count":63},{"score":"Pale Fuchsia Tortie-Standing","count":50},{"score":"Pale Cyan Spotted-Sleeping","count":65},{"score":"Pale Yellow Tabby-Sleeping","count":68},{"score":"Orange Tabby-Pouncing","count":78},{"score":"Red Pure-Sleeping","count":90},{"score":"Pale Teal Spotted-Sleeping","count":64},{"score":"Orange Spotted-Pouncing","count":87},{"score":"Pale Purple Tortie-Sleeping","count":65},{"score":"Pale Cyan Tabby-Standing","count":47},{"score":"Sky Blue Tortie-Pouncing","count":86},{"score":"Chartreuse Spotted-Pouncing","count":68},{"score":"Teal Tortie-Stalking","count":74},{"score":"Pale Orange Pure-Standing","count":64},{"score":"Blue Tabby-Sleeping","count":66},{"score":"Pale Green Pure-Sleeping","count":48},{"score":"Pale Green Spotted-Sleeping","count":60},{"score":"Pale Magenta Pure-Pouncing","count":80},{"score":"Magenta Pure-Stalking","count":73},{"score":"Pale Yellow Spotted-Pouncing","count":51},{"score":"Orange Tabby-Sleeping","count":81},{"score":"Red Tortie-Stalking","count":85},{"score":"Pale Sky Blue Tabby-Stalking","count":52},{"score":"Teal Tortie-Pouncing","count":65},{"score":"Pale Cyan Pure-Standing","count":65},{"score":"Pale Sky Blue Tabby-Sleeping","count":66},{"score":"Pale Teal Pure-Stalking","count":66},{"score":"Fuchsia Pure-Sleeping","count":73},{"score":"Purple Tortie-Pouncing","count":74},{"score":"Pale Orange Tabby-Pouncing","count":51},{"score":"Blue Pure-Standing","count":63},{"score":"Chartreuse Spotted-Stalking","count":53},{"score":"Chartreuse Tortie-Sleeping","count":55},{"score":"Pale Red Pure-Stalking","count":71},{"score":"Blue Tortie-Sleeping","count":74},{"score":"Magenta Tabby-Stalking","count":62},{"score":"Pale Magenta Tortie-Sleeping","count":72},{"score":"Pale Purple Spotted-Standing","count":62},{"score":"Pale Teal Spotted-Standing","count":68},{"score":"Pale Blue Pure-Standing","count":92},{"score":"Yellow Spotted-Pouncing","count":73},{"score":"Pale Orange Spotted-Pouncing","count":78},{"score":"Green Pure-Pouncing","count":49},{"score":"Pale Sky Blue Spotted-Stalking","count":74},{"score":"Orange Pure-Sleeping","count":62},{"score":"Pale Fuchsia Pure-Stalking","count":56},{"score":"Green Pure-Standing","count":66},{"score":"Pale Sky Blue Spotted-Sleeping","count":50},{"score":"Pale Blue Tortie-Sleeping","count":73},{"score":"Blue Tabby-Standing","count":63},{"score":"Blue Pure-Stalking","count":60},{"score":"Fuchsia Tabby-Pouncing","count":71},{"score":"Yellow Pure-Standing","count":77},{"score":"Sky Blue Spotted-Stalking","count":75},{"score":"Chartreuse Tabby-Sleeping","count":63},{"score":"Pale Yellow Tabby-Pouncing","count":58},{"score":"Pale Orange Tabby-Stalking","count":60},{"score":"Magenta Pure-Pouncing","count":66},{"score":"Fuchsia Spotted-Stalking","count":67},{"score":"Green Tabby-Sleeping","count":54},{"score":"Pale Sky Blue Pure-Stalking","count":70},{"score":"Yellow Spotted-Standing","count":61},{"score":"Pale Orange Tortie-Stalking","count":66},{"score":"Yellow Tabby-Pouncing","count":85},{"score":"Sky Blue Pure-Sleeping","count":69},{"score":"Pale Purple Tabby-Stalking","count":59},{"score":"Chartreuse Spotted-Standing","count":56},{"score":"Pale Teal Tortie-Sleeping","count":59},{"score":"Pale Orange Tortie-Standing","count":77},{"score":"Magenta Pure-Standing","count":66},{"score":"Green Tabby-Stalking","count":69},{"score":"Yellow Pure-Pouncing","count":71},{"score":"Orange Tabby-Standing","count":70},{"score":"Magenta Spotted-Stalking","count":56},{"score":"Pale Teal Pure-Pouncing","count":72},{"score":"Pale Blue Tortie-Pouncing","count":68},{"score":"Pale Cyan Spotted-Pouncing","count":67},{"score":"Blue Pure-Sleeping","count":62},{"score":"Pale Red Tabby-Pouncing","count":76},{"score":"Green Tabby-Pouncing","count":51},{"score":"Pale Teal Tabby-Sleeping","count":60},{"score":"Sky Blue Tabby-Sleeping","count":62},{"score":"Pale Yellow Pure-Sleeping","count":66},{"score":"Magenta Spotted-Pouncing","count":65},{"score":"Pale Magenta Tabby-Sleeping","count":66},{"score":"Chartreuse Tortie-Pouncing","count":78},{"score":"Magenta Tortie-Pouncing","count":59},{"score":"Magenta Tortie-Stalking","count":66},{"score":"Sky Blue Tabby-Pouncing","count":67},{"score":"Pale Chartreuse Tabby-Sleeping","count":53},{"score":"Purple Spotted-Sleeping","count":68},{"score":"Green Pure-Sleeping","count":60},{"score":"Pale Purple Spotted-Pouncing","count":68},{"score":"Pale Red Tortie-Stalking","count":71},{"score":"Pale Green Tabby-Stalking","count":74},{"score":"Purple Tabby-Pouncing","count":58},{"score":"Orange Tortie-Pouncing","count":89},{"score":"Fuchsia Tabby-Standing","count":72},{"score":"Pale Green Tortie-Stalking","count":57},{"score":"Orange Tortie-Stalking","count":68},{"score":"Pale Red Tabby-Stalking","count":75},{"score":"Magenta Tabby-Pouncing","count":73},{"score":"Pale Sky Blue Tortie-Stalking","count":69},{"score":"Pale Chartreuse Spotted-Pouncing","count":57},{"score":"Green Spotted-Standing","count":58},{"score":"Fuchsia Tabby-Stalking","count":63},{"score":"Blue Tortie-Standing","count":72},{"score":"Blue Tortie-Stalking","count":69},{"score":"Chartreuse Tortie-Standing","count":55},{"score":"Pale Blue Spotted-Pouncing","count":79},{"score":"Pale Teal Pure-Standing","count":62},{"score":"Fuchsia Tabby-Sleeping","count":72},{"score":"Purple Pure-Standing","count":54},{"score":"Blue Spotted-Standing","count":70},{"score":"Blue Tabby-Pouncing","count":64},{"score":"Pale Fuchsia Tortie-Stalking","count":61},{"score":"Pale Orange Tabby-Standing","count":54},{"score":"Yellow Tabby-Stalking","count":54},{"score":"Pale Teal Spotted-Stalking","count":53},{"score":"Pale Cyan Pure-Sleeping","count":64},{"score":"Red Spotted-Sleeping","count":68},{"score":"Pale Magenta Tabby-Stalking","count":70},{"score":"Pale Orange Pure-Sleeping","count":58},{"score":"Yellow Spotted-Sleeping","count":64},{"score":"Pale Blue Spotted-Standing","count":52},{"score":"Pale Cyan Tortie-Pouncing","count":71},{"score":"Pale Sky Blue Tortie-Pouncing","count":71},{"score":"Pale Chartreuse Tabby-Standing","count":62},{"score":"Blue Spotted-Stalking","count":69},{"score":"Teal Tortie-Standing","count":56},{"score":"Pale Blue Pure-Sleeping","count":70},{"score":"Red Spotted-Standing","count":74},{"score":"Pale Red Spotted-Pouncing","count":75},{"score":"Pale Magenta Tortie-Stalking","count":57},{"score":"Purple Tabby-Stalking","count":65},{"score":"Pale Fuchsia Tortie-Sleeping","count":63},{"score":"Pale Chartreuse Pure-Sleeping","count":53},{"score":"Cyan Pure-Sleeping","count":58},{"score":"Red Tortie-Pouncing","count":61},{"score":"Pale Blue Tabby-Standing","count":78},{"score":"Pale Green Tabby-Standing","count":63},{"score":"Pale Cyan Tabby-Pouncing","count":65},{"score":"Blue Tortie-Pouncing","count":80},{"score":"Yellow Tortie-Sleeping","count":66},{"score":"Pale Teal Pure-Sleeping","count":45},{"score":"Pale Fuchsia Spotted-Stalking","count":62},{"score":"Orange Spotted-Sleeping","count":67},{"score":"Purple Tortie-Stalking","count":82},{"score":"Green Spotted-Pouncing","count":62},{"score":"Green Tortie-Standing","count":47},{"score":"Pale Teal Tortie-Standing","count":63},{"score":"Sky Blue Tortie-Standing","count":78},{"score":"Teal Pure-Stalking","count":53},{"score":"Pale Magenta Tabby-Pouncing","count":67},{"score":"Pale Red Tortie-Pouncing","count":67},{"score":"Yellow Pure-Sleeping","count":65},{"score":"Purple Spotted-Stalking","count":69},{"score":"Pale Blue Pure-Pouncing","count":76}]